qmatic/__init__.py
qmatic/dists.py
qmatic/example.py
qmatic/lindley.py
qmatic/queue_approx.py
QMatic-0.0.1.dist-info/LICENSE
QMatic-0.0.1.dist-info/METADATA
QMatic-0.0.1.dist-info/WHEEL
QMatic-0.0.1.dist-info/top_level.txt
QMatic-0.0.1.dist-info/RECORD
