Metadata-Version: 2.1
Name: QMatic
Version: 0.0.1
Summary: Mathematical functions for queueing theory.
Author-email: Galen Seilis <galen.seilis@seilis.ca>
Project-URL: Homepage, https://github.com/galenseilis/qmatic
Project-URL: Issues, https://github.com/galenseilis/qmatic/issues
Classifier: Programming Language :: Python :: 3
Classifier: License :: OSI Approved :: MIT License
Classifier: Operating System :: OS Independent
Requires-Python: >=3.8
License-File: LICENSE
